channels_yroom/__about__.py
channels_yroom/__init__.py
channels_yroom/admin.py
channels_yroom/apps.py
channels_yroom/channel.py
channels_yroom/conf.py
channels_yroom/consumer.py
channels_yroom/models.py
channels_yroom/proxy.py
channels_yroom/storage.py
channels_yroom/utils.py
channels_yroom/worker.py
channels_yroom/management/__init__.py
channels_yroom/management/commands/__init__.py
channels_yroom/management/commands/yroom.py
channels_yroom/migrations/0001_initial.py
channels_yroom/migrations/__init__.py
channels_yroom-0.0.6.dist-info/METADATA
channels_yroom-0.0.6.dist-info/WHEEL
channels_yroom-0.0.6.dist-info/licenses/LICENSE
channels_yroom-0.0.6.dist-info/RECORD
